odoo/addons/sale_coupon_criteria_multi_product/README.rst
odoo/addons/sale_coupon_criteria_multi_product/__init__.py
odoo/addons/sale_coupon_criteria_multi_product/__manifest__.py
odoo/addons/sale_coupon_criteria_multi_product/i18n/es.po
odoo/addons/sale_coupon_criteria_multi_product/i18n/sale_coupon_criteria_multi_product.pot
odoo/addons/sale_coupon_criteria_multi_product/models/__init__.py
odoo/addons/sale_coupon_criteria_multi_product/models/coupon_program.py
odoo/addons/sale_coupon_criteria_multi_product/readme/CONFIGURE.rst
odoo/addons/sale_coupon_criteria_multi_product/readme/CONTRIBUTORS.rst
odoo/addons/sale_coupon_criteria_multi_product/readme/DESCRIPTION.rst
odoo/addons/sale_coupon_criteria_multi_product/readme/USAGE.rst
odoo/addons/sale_coupon_criteria_multi_product/security/ir.model.access.csv
odoo/addons/sale_coupon_criteria_multi_product/static/description/icon.png
odoo/addons/sale_coupon_criteria_multi_product/static/description/icon.svg
odoo/addons/sale_coupon_criteria_multi_product/static/description/index.html
odoo/addons/sale_coupon_criteria_multi_product/tests/__init__.py
odoo/addons/sale_coupon_criteria_multi_product/tests/test_sale_coupon_criteria_multi_product.py
odoo_addon_sale_coupon_criteria_multi_product-15.0.1.1.0.dist-info/METADATA
odoo_addon_sale_coupon_criteria_multi_product-15.0.1.1.0.dist-info/WHEEL
odoo_addon_sale_coupon_criteria_multi_product-15.0.1.1.0.dist-info/top_level.txt
odoo_addon_sale_coupon_criteria_multi_product-15.0.1.1.0.dist-info/RECORD
